statsim/__init__.py
statsim-0.0.1.dev0.dist-info/METADATA
statsim-0.0.1.dev0.dist-info/WHEEL
statsim-0.0.1.dev0.dist-info/licenses/LICENSE
statsim-0.0.1.dev0.dist-info/RECORD
