Metadata-Version: 2.4
Name: statsim
Version: 0.0.1.dev0
Summary: Work-in-progress. Nothing to see yet
Author-email: Anton Zemlyansky <anton.zemlyansky@gmail.com>
License-Expression: MIT
License-File: LICENSE
Classifier: Development Status :: 2 - Pre-Alpha
Classifier: Programming Language :: Python :: 3
Requires-Python: >=3.9
